evaluation_system/__init__.py
evaluation_system/api/__init__.py
evaluation_system/api/parameters.py
evaluation_system/api/plugin.py
evaluation_system/api/plugin_manager.py
evaluation_system/api/user_data.py
evaluation_system/api/workload_manager/__init__.py
evaluation_system/api/workload_manager/core.py
evaluation_system/api/workload_manager/local.py
evaluation_system/api/workload_manager/lsf.py
evaluation_system/api/workload_manager/moab.py
evaluation_system/api/workload_manager/oar.py
evaluation_system/api/workload_manager/pbs.py
evaluation_system/api/workload_manager/sge.py
evaluation_system/api/workload_manager/slurm.py
evaluation_system/fuse/__init__.py
evaluation_system/fuse/esgf2fs.py
evaluation_system/fuse/esgf2solr_crawl.py
evaluation_system/fuse/esgf_crawl_config.py
evaluation_system/misc/__init__.py
evaluation_system/misc/config.py
evaluation_system/misc/exceptions.py
evaluation_system/misc/utils.py
evaluation_system/model/__init__.py
evaluation_system/model/db.py
evaluation_system/model/esgf.py
evaluation_system/model/file.py
evaluation_system/model/repository.py
evaluation_system/model/solr.py
evaluation_system/model/solr_core.py
evaluation_system/model/user.py
evaluation_system/model/history/__init__.py
evaluation_system/model/history/models.py
evaluation_system/model/plugins/__init__.py
evaluation_system/model/plugins/models.py
evaluation_system/model/solr_models/__init__.py
evaluation_system/model/solr_models/models.py
evaluation_system/settings/__init__.py
evaluation_system/settings/database.py
evaluation_system/tests/__init__.py
evaluation_system/tests/cli_argcomplete_test.py
evaluation_system/tests/cli_help_test.py
evaluation_system/tests/conftest.py
evaluation_system/tests/crawl_my_data_test.py
evaluation_system/tests/databrowser_test.py
evaluation_system/tests/db_test.py
evaluation_system/tests/esgf_test.py
evaluation_system/tests/file_test.py
evaluation_system/tests/history_command_test.py
evaluation_system/tests/history_models_test.py
freva-2307.0.2.dist-info/LICENSE.md
freva-2307.0.2.dist-info/METADATA
freva-2307.0.2.dist-info/WHEEL
freva-2307.0.2.dist-info/entry_points.txt
freva-2307.0.2.dist-info/top_level.txt
freva-2307.0.2.dist-info/RECORD
