Metadata-Version: 2.1
Name: freva
Version: 2307.0.2
Summary: Free Evaluation and Analysis Framework (Freva) 
Author: German Climate Computing Centre (DKRZ)
Maintainer: Climate Informatics and Technology (CLINT)
License: BSD-3-Clause
Project-URL: Documentation, https://freva.gitlab-pages.dkrz.de/evaluation_system/sphinx_docs/index.html
Project-URL: Release notes, https://freva.gitlab-pages.dkrz.de/evaluation_system/sphinx_docs/whats-new.html
Project-URL: Issues, https://gitlab.dkrz.de/freva/evaluation_system/-/issues
Project-URL: Source, https://gitlab.dkrz.de/freva/evaluation_system
Classifier: Development Status :: 4 - Beta
Classifier: Environment :: Console
Classifier: Intended Audience :: Developers
Classifier: Intended Audience :: Science/Research
Classifier: License :: OSI Approved :: BSD License
Classifier: Operating System :: POSIX :: Linux
Classifier: Programming Language :: Python :: 3
Classifier: Programming Language :: Python :: 3.7
Classifier: Programming Language :: Python :: 3.8
Classifier: Programming Language :: Python :: 3.9
Classifier: Programming Language :: Python :: 3.10
Classifier: Topic :: Scientific/Engineering :: Physics
Classifier: Topic :: Scientific/Engineering :: Atmospheric Science
Requires-Python: >=3.7
License-File: LICENSE.md
Requires-Dist: appdirs
Requires-Dist: GitPython
Requires-Dist: dask
Requires-Dist: Django
Requires-Dist: humanize
Requires-Dist: h5netcdf
Requires-Dist: lazy-import
Requires-Dist: mysqlclient
Requires-Dist: metadata-inspector
Requires-Dist: netCDF4
Requires-Dist: numpy
Requires-Dist: pymysql
Requires-Dist: pandas
Requires-Dist: Pillow
Requires-Dist: PyPDF2 (!=2.10.1)
Requires-Dist: requests
Requires-Dist: toml
Requires-Dist: toolz
Requires-Dist: typing-extensions
Requires-Dist: xarray
Provides-Extra: docs
Requires-Dist: bash-kernel ; extra == 'docs'
Requires-Dist: cartopy ; extra == 'docs'
Requires-Dist: cftime ; extra == 'docs'
Requires-Dist: cf-xarray ; extra == 'docs'
Requires-Dist: furo ; extra == 'docs'
Requires-Dist: ipython ; extra == 'docs'
Requires-Dist: ipykernel ; extra == 'docs'
Requires-Dist: nbsphinx ; extra == 'docs'
Requires-Dist: pint ; extra == 'docs'
Requires-Dist: pint-xarray ; extra == 'docs'
Requires-Dist: recommonmark ; extra == 'docs'
Requires-Dist: sphinx ; extra == 'docs'
Requires-Dist: sphinxcontrib-github-alt ; extra == 'docs'
Requires-Dist: sphinx-execute-code-python3 ; extra == 'docs'
Requires-Dist: xarray ; extra == 'docs'
Requires-Dist: h5netcdf ; extra == 'docs'
Provides-Extra: test
Requires-Dist: allure-pytest ; extra == 'test'
Requires-Dist: black ; extra == 'test'
Requires-Dist: django-stubs ; extra == 'test'
Requires-Dist: django-stubs-ext ; extra == 'test'
Requires-Dist: h5netcdf ; extra == 'test'
Requires-Dist: mock ; extra == 'test'
Requires-Dist: mypy ; extra == 'test'
Requires-Dist: nbval ; extra == 'test'
Requires-Dist: nbformat ; extra == 'test'
Requires-Dist: pep257 ; extra == 'test'
Requires-Dist: pytest ; extra == 'test'
Requires-Dist: pytest-html ; extra == 'test'
Requires-Dist: pytest-env ; extra == 'test'
Requires-Dist: pytest-cov ; extra == 'test'
Requires-Dist: python-swiftclient ; extra == 'test'
Requires-Dist: requests-mock ; extra == 'test'
Requires-Dist: testpath ; extra == 'test'
Requires-Dist: types-mock ; extra == 'test'
Requires-Dist: types-requests ; extra == 'test'
Requires-Dist: types-toml ; extra == 'test'
Requires-Dist: types-urllib3 ; extra == 'test'
